wordsearch/__init__.py
wordsearch/alphabets.py
wordsearch/wordsearch.py
wordsearch_gen-0.1.3.dist-info/licenses/LICENSE
wordsearch_gen-0.1.3.dist-info/METADATA
wordsearch_gen-0.1.3.dist-info/WHEEL
wordsearch_gen-0.1.3.dist-info/top_level.txt
wordsearch_gen-0.1.3.dist-info/RECORD
