Metadata-Version: 2.4
Name: wordsearch-gen
Version: 0.1.3
Summary: A customizable word search puzzle generator.
Home-page: https://github.com/saweekmusic/wordsearch
Author: Sviatoslav Trofymenko
Author-email: sviatoslavtrofymenko@icloud.com
License: MIT
Project-URL: Bug Tracker, https://github.com/saweekmusic/wordsearch/issues
Classifier: Programming Language :: Python :: 3
Classifier: License :: OSI Approved :: MIT License
Classifier: Operating System :: OS Independent
Requires-Python: >=3.7
License-File: LICENSE
Dynamic: author
Dynamic: author-email
Dynamic: classifier
Dynamic: description
Dynamic: description-content-type
Dynamic: home-page
Dynamic: license
Dynamic: license-file
Dynamic: project-url
Dynamic: requires-python
Dynamic: summary
